{"version":1,"resource":"vscode-remote://ssh-remote%2Bhybrid2_master/root/kube/06/labs/deploy-lab.yml","entries":[{"id":"QRRS.yml","timestamp":1733116776206},{"id":"KlPS.yml","timestamp":1733116841794},{"id":"DMsT.yml","timestamp":1733116861380},{"id":"GSK3.yml","timestamp":1733116887866},{"id":"onFv.yml","timestamp":1733116899169},{"id":"KYYi.yml","timestamp":1733116912923},{"id":"7ZJz.yml","timestamp":1733116927114},{"id":"2M8x.yml","timestamp":1733116944503},{"id":"YPww.yml","timestamp":1733117060586},{"id":"KX30.yml","timestamp":1733117103333},{"id":"VCaX.yml","timestamp":1733117146361}]}